PyClassJVM/__init__.py
PyClassJVM/attributes.py
PyClassJVM/cp_info.py
PyClassJVM/field_info.py
PyClassJVM/flags.py
PyClassJVM/method.py
PyClassJVM-0.1.0.dist-info/LICENSE
PyClassJVM-0.1.0.dist-info/METADATA
PyClassJVM-0.1.0.dist-info/WHEEL
PyClassJVM-0.1.0.dist-info/top_level.txt
PyClassJVM-0.1.0.dist-info/RECORD
