Metadata-Version: 2.1
Name: PyClassJVM
Version: 0.1.0
Summary: JVM class file reader
Author-email: Olivia Ryan <olivia.r.dev@gmail.com>
License: MIT License
Project-URL: Repository, https://github.com/olivi-r/PyClassJVM
Project-URL: Issues, https://github.com/olivi-r/PyClassJVM/issues
Classifier: Development Status :: 4 - Beta
Classifier: License :: OSI Approved :: MIT License
Classifier: Programming Language :: Python :: 3
Classifier: Programming Language :: Python :: 3.9
Classifier: Programming Language :: Python :: 3.10
Classifier: Programming Language :: Python :: 3.11
Classifier: Programming Language :: Python :: 3.12
Requires-Python: >=3.9
License-File: LICENSE
